{
    "process": "meteoblue-precipitation-retriever-process",
    "payload": {
        "inputs": {
            "debug": true,
            "async": true,
            "cron_invocation": true,
            
            "token": null,
            
            "service": "basic-5min",

            "lat_range": [ 45.48, 45.62 ],
            "long_range": [ 11.47, 11.62 ],

            "grid_res": 2000,
            
            "time_range": null,
            "strict_time_range": true
        }
    } 	
}